pyhms/__init__.py
pyhms/cluster/__init__.py
pyhms/cluster/cluster.py
pyhms/cluster/consolidator.py
pyhms/cluster/kriging.py
pyhms/cluster/landscape_approximator.py
pyhms/cluster/local_basin_agent.py
pyhms/cluster/merge_conditions.py
pyhms/config.py
pyhms/core/__init__.py
pyhms/core/individual.py
pyhms/core/population.py
pyhms/core/problem.py
pyhms/demes/__init__.py
pyhms/demes/abstract_deme.py
pyhms/demes/cma_deme.py
pyhms/demes/de_deme.py
pyhms/demes/ea_deme.py
pyhms/demes/initialize.py
pyhms/demes/lhs_deme.py
pyhms/demes/local_deme.py
pyhms/demes/shade_deme.py
pyhms/demes/single_pop_eas/__init__.py
pyhms/demes/single_pop_eas/common.py
pyhms/demes/single_pop_eas/de.py
pyhms/demes/single_pop_eas/multiwinner.py
pyhms/demes/single_pop_eas/sea.py
pyhms/demes/sobol_deme.py
pyhms/hms.py
pyhms/initializers.py
pyhms/logging_.py
pyhms/sprout/__init__.py
pyhms/sprout/sprout_candidates.py
pyhms/sprout/sprout_filters.py
pyhms/sprout/sprout_generators.py
pyhms/sprout/sprout_mechanisms.py
pyhms/stop_conditions/__init__.py
pyhms/stop_conditions/gsc.py
pyhms/stop_conditions/lsc.py
pyhms/stop_conditions/usc.py
pyhms/test/__init__.py
pyhms/test/__main__.py
pyhms/tree.py
pyhms/utils/__init__.py
pyhms/utils/cache.py
pyhms/utils/clusterization.py
pyhms/utils/covariance_estimate.py
pyhms/utils/deme_performance.py
pyhms/utils/distances.py
pyhms/utils/parameter_initializer.py
pyhms/utils/print_tree.py
pyhms/utils/r5s.py
pyhms/utils/redundancy_factor.py
pyhms/utils/visualisation/__init__.py
pyhms/utils/visualisation/animate.py
pyhms/utils/visualisation/dimensionality_reduction.py
pyhms/utils/visualisation/grid.py
pyhms-1.0.0.dist-info/LICENSE
pyhms-1.0.0.dist-info/METADATA
pyhms-1.0.0.dist-info/WHEEL
pyhms-1.0.0.dist-info/RECORD
