Metadata-Version: 2.3
Name: pyhms
Version: 1.0.0
Summary: The HMS (Hierarchic Memetic Strategy) is a composite global optimization strategy consisting of a multi-population evolutionary strategy and some auxiliary methods. The HMS makes use of a tree with a fixed maximal height and variable internal node degree. Each component population is governed by a particular evolutionary engine. This package provides a simple python implementation with examples of using different population engines.
License: MIT
Keywords: optimization,HMS
Author: Maciej Smołka
Author-email: smolka@agh.edu.pl
Requires-Python: >=3.10,<4.0
Classifier: Development Status :: 5 - Production/Stable
Classifier: Environment :: Console
Classifier: Framework :: IPython
Classifier: Framework :: Jupyter
Classifier: Intended Audience :: Education
Classifier: Intended Audience :: Other Audience
Classifier: Intended Audience :: Science/Research
Classifier: License :: OSI Approved :: MIT License
Classifier: Operating System :: OS Independent
Classifier: Programming Language :: Python :: 3
Classifier: Programming Language :: Python :: 3.10
Classifier: Programming Language :: Python :: 3.11
Classifier: Programming Language :: Python :: 3.12
Classifier: Programming Language :: Python :: 3.13
Classifier: Topic :: Scientific/Engineering
Classifier: Topic :: Scientific/Engineering :: Artificial Intelligence
Classifier: Topic :: Scientific/Engineering :: Mathematics
Requires-Dist: cma (>=3.2.2)
Requires-Dist: dill (>=0.3.8,<0.4.0)
Requires-Dist: graphviz (>=0.20.1,<0.21.0)
Requires-Dist: kaleido (==0.2.1)
Requires-Dist: matplotlib (>=3.5.1)
Requires-Dist: numpy (<2)
Requires-Dist: pandas (>=2.2.2,<3.0.0)
Requires-Dist: plotly (>=5.22.0,<6.0.0)
Requires-Dist: pykrige (>=1.7.2,<2.0.0)
Requires-Dist: scikit-learn (>=1.5.1,<2.0.0)
Requires-Dist: scipy (>=1.8.0)
Requires-Dist: setuptools (>=63.2.0)
Requires-Dist: structlog (>=24.1.0,<25.0.0)
Requires-Dist: treelib (>=1.7.0)
Project-URL: Repository, https://github.com/maciejsmolka/pyhms
